[
   {
      "image": "./src/assets/image1.svg",
      "title": "chair relaxed",
      "price": 13.5,
      "desc": "Lorem Ipsum is simply"
   },
   {
      "image": "./src/assets/image4.svg",
      "title": "chair relaxed",
      "price": 14.5,
      "desc": "Lorem Ipsum is simply"
   },
   {
      "image": "./src/assets/image1.svg",
      "title": "chair relaxed",
      "price": 15.5,
      "desc": "Lorem Ipsum is simply"
   },
   {
      "image": "./src/assets/image4.svg",
      "title": "chair relaxed",
      "price": 16.5,
      "desc": "Lorem Ipsum is simply"
   }
]
